<?xml version="1.0" encoding="utf-8"?>
<odoo>
    <data>
        <template id="calendar_meeting_public_mom_report">
            <t t-call="web.html_container">
                <t t-foreach="docs" t-as="o">
                <t t-call="web.external_layout">
                    <div class="page">
                        <h2>
                            Minutes of Meeting
                        </h2>
                        <p>
                            <span t-field="o.fal_public_mom"/>
                        </p>

                    </div>
                </t>
                </t>
            </t>
        </template>
    </data>
</odoo>
